onami/__init__.py
onami/__main__.py
onami/codeblocks.py
onami/cog.py
onami/exception_handling.py
onami/flags.py
onami/functools.py
onami/help_command.py
onami/hljs.py
onami/meta.py
onami/models.py
onami/modules.py
onami/paginators.py
onami/shell.py
onami/features/__init__.py
onami/features/baseclass.py
onami/features/filesystem.py
onami/features/guild.py
onami/features/invocation.py
onami/features/management.py
onami/features/python.py
onami/features/root_command.py
onami/features/shell.py
onami/features/voice.py
onami/features/youtube.py
onami/repl/__init__.py
onami/repl/compilation.py
onami/repl/disassembly.py
onami/repl/inspections.py
onami/repl/repl_builtins.py
onami/repl/scope.py
onami/repl/walkers.py
onami/shim/paginator_170.py
onami/shim/paginator_200.py
onami/shim/paginator_base.py
onami-2.3.2.dist-info/LICENSE
onami-2.3.2.dist-info/METADATA
onami-2.3.2.dist-info/WHEEL
onami-2.3.2.dist-info/top_level.txt
onami-2.3.2.dist-info/RECORD
