Metadata-Version: 2.1
Name: onami
Version: 2.3.2
Summary: A pythonic discord extension including useful tools for bot development and debugging.
Home-page: https://github.com/VincentRPS/Onami
Author: VincentRPS
License: MIT
Download-URL: https://github.com/VincentRPS/Onami/archive/2.3.2.tar.gz
Project-URL: Documentation, https://onami.readthedocs.io/en/latest/
Project-URL: Code, https://github.com/VincentRPS/Onami
Project-URL: Issue tracker, https://github.com/VincentRPS/Onami/issues
Project-URL: Pull tracker, https://github.com/VincentRPS/Onami/pulls
Project-URL: Projects, https://github.com/VincentRPS/Onami/projects
Keywords: onami discord.py discord cog repl extension onami
Platform: UNKNOWN
Classifier: Development Status :: 5 - Production/Stable
Classifier: Framework :: AsyncIO
Classifier: Intended Audience :: Developers
Classifier: License :: OSI Approved :: MIT License
Classifier: Natural Language :: English
Classifier: Operating System :: OS Independent
Classifier: Programming Language :: Python :: 3 :: Only
Classifier: Programming Language :: Python :: 3.8
Classifier: Programming Language :: Python :: 3.9
Classifier: Topic :: Communications :: Chat
Classifier: Topic :: Internet
Classifier: Topic :: Software Development :: Debuggers
Classifier: Topic :: Software Development :: Testing
Classifier: Topic :: Utilities
Requires-Python: >=3.8.0
License-File: LICENSE
Requires-Dist: braceexpand (>=0.1.7)
Requires-Dist: click (>=8.0.1)
Requires-Dist: import-expression (<2.0.0,>=1.0.0)
Requires-Dist: importlib-metadata (>=3.7.0) ; python_version < "3.10"
Provides-Extra: docs
Requires-Dist: sphinx (>=3.5.4) ; extra == 'docs'
Requires-Dist: sphinxcontrib-asyncio ; extra == 'docs'
Provides-Extra: procinfo
Requires-Dist: psutil ; extra == 'procinfo'
Provides-Extra: test
Requires-Dist: click ; extra == 'test'
Requires-Dist: coverage ; extra == 'test'
Requires-Dist: flake8 ; extra == 'test'
Requires-Dist: isort ; extra == 'test'
Requires-Dist: pylint ; extra == 'test'
Requires-Dist: pytest ; extra == 'test'
Requires-Dist: pytest-cov ; extra == 'test'
Requires-Dist: pytest-mock ; extra == 'test'
Provides-Extra: voice
Requires-Dist: youtube-dl ; extra == 'voice'
